{
	"meta_info": {
		"dataset_name": "coco",
		"num_keypoints": 17,
		"keypoint_id2name": {
			"0": "nose",
			"1": "left_eye",
			"2": "right_eye",
			"3": "left_ear",
			"4": "right_ear",
			"5": "left_shoulder",
			"6": "right_shoulder",
			"7": "left_elbow",
			"8": "right_elbow",
			"9": "left_wrist",
			"10": "right_wrist",
			"11": "left_hip",
			"12": "right_hip",
			"13": "left_knee",
			"14": "right_knee",
			"15": "left_ankle",
			"16": "right_ankle"
		},
		"keypoint_name2id": {
			"nose": 0,
			"left_eye": 1,
			"right_eye": 2,
			"left_ear": 3,
			"right_ear": 4,
			"left_shoulder": 5,
			"right_shoulder": 6,
			"left_elbow": 7,
			"right_elbow": 8,
			"left_wrist": 9,
			"right_wrist": 10,
			"left_hip": 11,
			"right_hip": 12,
			"left_knee": 13,
			"right_knee": 14,
			"left_ankle": 15,
			"right_ankle": 16
		},
		"upper_body_ids": [
			0,
			1,
			2,
			3,
			4,
			5,
			6,
			7,
			8,
			9,
			10
		],
		"lower_body_ids": [
			11,
			12,
			13,
			14,
			15,
			16
		],
		"flip_indices": [
			0,
			2,
			1,
			4,
			3,
			6,
			5,
			8,
			7,
			10,
			9,
			12,
			11,
			14,
			13,
			16,
			15
		],
		"flip_pairs": [
			[
				2,
				1
			],
			[
				1,
				2
			],
			[
				4,
				3
			],
			[
				3,
				4
			],
			[
				6,
				5
			],
			[
				5,
				6
			],
			[
				8,
				7
			],
			[
				7,
				8
			],
			[
				10,
				9
			],
			[
				9,
				10
			],
			[
				12,
				11
			],
			[
				11,
				12
			],
			[
				14,
				13
			],
			[
				13,
				14
			],
			[
				16,
				15
			],
			[
				15,
				16
			]
		],
		"keypoint_colors": {
			"__ndarray__": [
				[
					51,
					153,
					255
				],
				[
					51,
					153,
					255
				],
				[
					51,
					153,
					255
				],
				[
					51,
					153,
					255
				],
				[
					51,
					153,
					255
				],
				[
					0,
					255,
					0
				],
				[
					255,
					128,
					0
				],
				[
					0,
					255,
					0
				],
				[
					255,
					128,
					0
				],
				[
					0,
					255,
					0
				],
				[
					255,
					128,
					0
				],
				[
					0,
					255,
					0
				],
				[
					255,
					128,
					0
				],
				[
					0,
					255,
					0
				],
				[
					255,
					128,
					0
				],
				[
					0,
					255,
					0
				],
				[
					255,
					128,
					0
				]
			],
			"dtype": "uint8",
			"shape": [
				17,
				3
			],
			"Corder": true
		},
		"num_skeleton_links": 19,
		"skeleton_links": [
			[
				15,
				13
			],
			[
				13,
				11
			],
			[
				16,
				14
			],
			[
				14,
				12
			],
			[
				11,
				12
			],
			[
				5,
				11
			],
			[
				6,
				12
			],
			[
				5,
				6
			],
			[
				5,
				7
			],
			[
				6,
				8
			],
			[
				7,
				9
			],
			[
				8,
				10
			],
			[
				1,
				2
			],
			[
				0,
				1
			],
			[
				0,
				2
			],
			[
				1,
				3
			],
			[
				2,
				4
			],
			[
				3,
				5
			],
			[
				4,
				6
			]
		],
		"skeleton_link_colors": {
			"__ndarray__": [
				[
					0,
					255,
					0
				],
				[
					0,
					255,
					0
				],
				[
					255,
					128,
					0
				],
				[
					255,
					128,
					0
				],
				[
					51,
					153,
					255
				],
				[
					51,
					153,
					255
				],
				[
					51,
					153,
					255
				],
				[
					51,
					153,
					255
				],
				[
					0,
					255,
					0
				],
				[
					255,
					128,
					0
				],
				[
					0,
					255,
					0
				],
				[
					255,
					128,
					0
				],
				[
					51,
					153,
					255
				],
				[
					51,
					153,
					255
				],
				[
					51,
					153,
					255
				],
				[
					51,
					153,
					255
				],
				[
					51,
					153,
					255
				],
				[
					51,
					153,
					255
				],
				[
					51,
					153,
					255
				]
			],
			"dtype": "uint8",
			"shape": [
				19,
				3
			],
			"Corder": true
		},
		"dataset_keypoint_weights": {
			"__ndarray__": [
				1.0,
				1.0,
				1.0,
				1.0,
				1.0,
				1.0,
				1.0,
				1.2000000476837158,
				1.2000000476837158,
				1.5,
				1.5,
				1.0,
				1.0,
				1.2000000476837158,
				1.2000000476837158,
				1.5,
				1.5
			],
			"dtype": "float32",
			"shape": [
				17
			]
		},
		"sigmas": {
			"__ndarray__": [
				0.026000000536441803,
				0.02500000037252903,
				0.02500000037252903,
				0.03500000014901161,
				0.03500000014901161,
				0.07900000363588333,
				0.07900000363588333,
				0.07199999690055847,
				0.07199999690055847,
				0.06199999898672104,
				0.06199999898672104,
				0.10700000077486038,
				0.10700000077486038,
				0.08699999749660492,
				0.08699999749660492,
				0.08900000154972076,
				0.08900000154972076
			],
			"dtype": "float32",
			"shape": [
				17
			]
		}
	},
	"instance_info": [
		{
			"keypoints": [
				[
					1455.0250487958986,
					714.1385884064227
				],
				[
					1459.136017515724,
					709.2815149662617
				],
				[
					1452.9423019097064,
					710.3538623533926
				],
				[
					1469.1391443715715,
					707.8690966492397
				],
				[
					1452.1790255803398,
					711.2515395957189
				],
				[
					1481.83699932716,
					724.1848276396826
				],
				[
					1455.4553205097816,
					728.3980787681371
				],
				[
					1491.632800027917,
					740.6247757476799
				],
				[
					1451.0258534575605,
					751.5399723067447
				],
				[
					1467.2804769985948,
					733.7446608483469
				],
				[
					1454.1156233013626,
					736.92501931882
				],
				[
					1482.021176144979,
					776.0607652576374
				],
				[
					1462.8409115018687,
					776.0546902892113
				],
				[
					1486.704265050574,
					808.7020206086759
				],
				[
					1464.8402189858507,
					807.9216062437322
				],
				[
					1496.0338229793024,
					834.067690089478
				],
				[
					1466.7157617435441,
					837.7363789166501
				]
			],
			"keypoint_scores": [
				0.780549943447113,
				0.7734235525131226,
				0.8327605724334717,
				0.8393955230712891,
				0.6469154357910156,
				0.756744921207428,
				0.7289005517959595,
				0.4353831112384796,
				0.4793957471847534,
				0.3529846668243408,
				0.3740188181400299,
				0.5347836017608643,
				0.5128336548805237,
				0.5019272565841675,
				0.432292640209198,
				0.4820537567138672,
				0.581138014793396
			],
			"bbox": [
				[
					1445.737548828125,
					683.5523681640625,
					1508.906005859375,
					840.0101318359375
				]
			],
			"bbox_score": 1.0
		},
		{
			"keypoints": [
				[
					194.65295551324255,
					772.0302802822678
				],
				[
					195.71749519519915,
					766.4611510125417
				],
				[
					190.53324480252616,
					768.2834119281719
				],
				[
					204.33959300127907,
					760.0650094295457
				],
				[
					188.9378537900376,
					765.9780937747752
				],
				[
					219.17086041779777,
					775.2039226140894
				],
				[
					206.09574387252871,
					779.3598851274437
				],
				[
					236.96681466716666,
					799.606998100777
				],
				[
					204.25780853692459,
					803.242970492458
				],
				[
					232.3266713405759,
					818.4378408016637
				],
				[
					194.01154422073034,
					816.9718412889966
				],
				[
					224.75109883255766,
					832.3188221150776
				],
				[
					213.67839495730624,
					831.9925254552259
				],
				[
					213.54525761969978,
					878.6179159640368
				],
				[
					214.598498132239,
					877.0112468918503
				],
				[
					216.85740264680516,
					915.0829439537151
				],
				[
					216.9530088533412,
					913.3525373828347
				]
			],
			"keypoint_scores": [
				0.9336172342300415,
				0.9040392637252808,
				0.9102346897125244,
				0.8727990388870239,
				0.5567473769187927,
				0.6221699714660645,
				0.614120364189148,
				0.7533000111579895,
				0.6818852424621582,
				0.59114670753479,
				0.6265033483505249,
				0.5734655857086182,
				0.5328800678253174,
				0.6142336130142212,
				0.3991207480430603,
				0.5816540122032166,
				0.49753081798553467
			],
			"bbox": [
				[
					184.86410522460938,
					744.7815551757812,
					250.13575744628906,
					928.4493408203125
				]
			],
			"bbox_score": 1.0
		},
		{
			"keypoints": [
				[
					1363.2869658160093,
					742.2122748999576
				],
				[
					1364.3041869568133,
					735.9907891122358
				],
				[
					1361.3915733046274,
					735.9195882650018
				],
				[
					1378.0284535975413,
					731.0136913184431
				],
				[
					1394.0580588366558,
					727.7093847025748
				],
				[
					1379.665388145593,
					757.7687966833926
				],
				[
					1409.6081576779623,
					750.5907019653491
				],
				[
					1373.1615778092355,
					798.9696044769759
				],
				[
					1424.8227673606907,
					748.0028986567188
				],
				[
					1359.5660323819463,
					822.3638497458564
				],
				[
					1422.4355875455644,
					729.3139233004065
				],
				[
					1382.5188566398945,
					825.7332374990755
				],
				[
					1407.5535227529397,
					821.7441576648326
				],
				[
					1369.794436807021,
					868.279715855532
				],
				[
					1399.3109250730151,
					863.9749639229997
				],
				[
					1379.943715984938,
					909.1295114987427
				],
				[
					1400.1820191779284,
					900.0880493015229
				]
			],
			"keypoint_scores": [
				0.6811050176620483,
				0.6329882144927979,
				0.4782125949859619,
				0.7665632963180542,
				0.6306207180023193,
				0.8411080241203308,
				0.7267194986343384,
				0.8668071031570435,
				0.7381296157836914,
				0.8992676734924316,
				0.7171969413757324,
				0.6766667366027832,
				0.6516255736351013,
				0.7597367763519287,
				0.5280686020851135,
				0.5759492516517639,
				0.5713979601860046
			],
			"bbox": [
				[
					1346.77099609375,
					701.447265625,
					1433.1038818359375,
					908.3671875
				]
			],
			"bbox_score": 1.0
		},
		{
			"keypoints": [
				[
					1728.8533801398737,
					582.5841292662705
				],
				[
					1729.3505763332917,
					580.5719951908478
				],
				[
					1729.623906753468,
					580.4950722345404
				],
				[
					1729.4107531762156,
					581.5093636763132
				],
				[
					1737.6129672429697,
					580.5723372486349
				],
				[
					1728.1723354214944,
					592.0829338537213
				],
				[
					1743.127382972788,
					590.4238768318652
				],
				[
					1726.6677835072908,
					602.7296643517786
				],
				[
					1748.0887434226809,
					602.879565754107
				],
				[
					1729.0601258579532,
					618.9957735706703
				],
				[
					1748.0734584978682,
					613.2473306067529
				],
				[
					1733.4450138252887,
					618.0932382479534
				],
				[
					1743.563513274758,
					617.0856961903212
				],
				[
					1738.0296022205137,
					637.4701044114439
				],
				[
					1743.1926525540493,
					636.175717699275
				],
				[
					1740.7896617504996,
					653.0572873230558
				],
				[
					1744.4008359491547,
					651.9034146126776
				]
			],
			"keypoint_scores": [
				0.664176344871521,
				0.7458674907684326,
				0.605414628982544,
				0.8563061952590942,
				0.8540663719177246,
				0.7709944248199463,
				0.7892154455184937,
				0.569208025932312,
				0.6701390743255615,
				0.478253573179245,
				0.5830286741256714,
				0.6504504084587097,
				0.7004034519195557,
				0.714809775352478,
				0.7499606013298035,
				0.6951534152030945,
				0.7658109664916992
			],
			"bbox": [
				[
					1724.314208984375,
					573.9171142578125,
					1753.7281494140625,
					662.0983276367188
				]
			],
			"bbox_score": 1.0
		},
		{
			"keypoints": [
				[
					1546.8514625100038,
					625.3668342811335
				],
				[
					1547.922037963122,
					623.5546516189601
				],
				[
					1548.0949324277096,
					623.2518716697407
				],
				[
					1550.1488935158295,
					623.6559409935255
				],
				[
					1552.6731959451881,
					622.7377821046532
				],
				[
					1555.9187199175103,
					630.6114489497166
				],
				[
					1552.149223405663,
					630.2237729956488
				],
				[
					1554.6695198547993,
					642.0580765492771
				],
				[
					1548.9108550017063,
					642.0041036612542
				],
				[
					1549.6994157065292,
					651.3644786259596
				],
				[
					1548.235847334274,
					651.0821419233781
				],
				[
					1555.1816565436682,
					651.6084108353068
				],
				[
					1554.528479761353,
					651.4667755170755
				],
				[
					1554.869073434928,
					667.921201869036
				],
				[
					1554.9787542144477,
					667.8635979592874
				],
				[
					1554.9620759075854,
					684.9696950724917
				],
				[
					1555.0892942312025,
					684.0932632173884
				]
			],
			"keypoint_scores": [
				0.546639084815979,
				0.5683776140213013,
				0.4767014980316162,
				0.6172201037406921,
				0.5933801531791687,
				0.49647262692451477,
				0.43561968207359314,
				0.3195187747478485,
				0.4587460160255432,
				0.3756539225578308,
				0.48954394459724426,
				0.4899553656578064,
				0.46229466795921326,
				0.5140244364738464,
				0.4782785475254059,
				0.5573895573616028,
				0.5478395223617554
			],
			"bbox": [
				[
					1545.052001953125,
					613.09326171875,
					1568.39111328125,
					687.876220703125
				]
			],
			"bbox_score": 1.0
		},
		{
			"keypoints": [
				[
					798.0762511134046,
					705.017129400623
				],
				[
					797.1498381595532,
					702.561303222631
				],
				[
					796.4601368503124,
					702.7415146172973
				],
				[
					791.2045211325228,
					703.4842222998192
				],
				[
					797.3715569820104,
					703.7258452717443
				],
				[
					785.664360194472,
					713.8450305801026
				],
				[
					801.0813620015929,
					714.6568954598998
				],
				[
					780.5228001406618,
					726.624872038152
				],
				[
					805.4139936956852,
					726.5381684273459
				],
				[
					782.3263071861323,
					738.3351392568286
				],
				[
					805.70901114855,
					740.0849950661983
				],
				[
					788.4568984065529,
					742.1084969657906
				],
				[
					799.5929019096682,
					742.1148452070443
				],
				[
					787.3934367126934,
					761.3954980129243
				],
				[
					802.313432588512,
					760.9351182670105
				],
				[
					784.9670382629092,
					780.262505822646
				],
				[
					803.7829006060728,
					780.242730215846
				]
			],
			"keypoint_scores": [
				0.5565688610076904,
				0.5487974882125854,
				0.5854382514953613,
				0.5510627627372742,
				0.6121283173561096,
				0.5670701265335083,
				0.5617220401763916,
				0.37740620970726013,
				0.2760158181190491,
				0.2199394553899765,
				0.12928465008735657,
				0.4890475273132324,
				0.44265538454055786,
				0.4186529517173767,
				0.38998374342918396,
				0.396394282579422,
				0.41096019744873047
			],
			"bbox": [
				[
					776.8843994140625,
					694.8120727539062,
					815.6683959960938,
					786.7784423828125
				]
			],
			"bbox_score": 1.0
		},
		{
			"keypoints": [
				[
					1525.1131659400746,
					628.4117284163096
				],
				[
					1525.4853204987653,
					627.1153104170537
				],
				[
					1524.1584520911565,
					627.1544406901355
				],
				[
					1526.3707082793744,
					628.0068310179174
				],
				[
					1522.781588605472,
					628.1932934535018
				],
				[
					1527.4580409450857,
					634.8383200032113
				],
				[
					1520.8311790052846,
					635.5138370025587
				],
				[
					1530.7986320070281,
					643.2480048454433
				],
				[
					1527.2058141644322,
					644.0122854677694
				],
				[
					1530.3897394293465,
					648.1972919698954
				],
				[
					1529.631310262245,
					646.9945280887603
				],
				[
					1527.2849402528686,
					651.6709245743738
				],
				[
					1523.420326047857,
					652.0313214967069
				],
				[
					1529.3515261600367,
					665.5260154338903
				],
				[
					1526.0853680403986,
					665.9415333112785
				],
				[
					1531.9165500761414,
					677.763468353294
				],
				[
					1530.7920682017834,
					678.3993438119984
				]
			],
			"keypoint_scores": [
				0.42999786138534546,
				0.4286169707775116,
				0.4141957759857178,
				0.3483982980251312,
				0.49036920070648193,
				0.4421881139278412,
				0.4438866376876831,
				0.49728769063949585,
				0.2674817442893982,
				0.3701373040676117,
				0.2940138876438141,
				0.5572987198829651,
				0.49367570877075195,
				0.6449978947639465,
				0.4454105794429779,
				0.6776106357574463,
				0.45873838663101196
			],
			"bbox": [
				[
					1515.008544921875,
					618.5692138671875,
					1538.473388671875,
					685.2842407226562
				]
			],
			"bbox_score": 1.0
		},
		{
			"keypoints": [
				[
					193.06965205071748,
					772.6642051196568
				],
				[
					194.4244969067742,
					764.0891131740894
				],
				[
					188.90238870333565,
					769.3946801637454
				],
				[
					204.41279989266098,
					756.6838914165772
				],
				[
					257.3149183041644,
					727.569298741443
				],
				[
					246.0318303687344,
					729.7607327898718
				],
				[
					207.89786845320674,
					729.737212665043
				],
				[
					255.40664817485708,
					765.7191550402869
				],
				[
					194.1427114413292,
					764.4536601384282
				],
				[
					217.7663094762185,
					760.3714692560025
				],
				[
					204.500277155022,
					759.9097374654874
				],
				[
					261.58402180667974,
					822.0768218512336
				],
				[
					248.62111471475976,
					822.7483908756016
				],
				[
					265.65917085094793,
					887.4588760133565
				],
				[
					265.79864008035116,
					888.1524646672465
				],
				[
					272.1773840260365,
					910.4433672068462
				],
				[
					273.50671450298853,
					909.1633458782342
				]
			],
			"keypoint_scores": [
				0.11920320987701416,
				0.1304353028535843,
				0.08832420408725739,
				0.08107146620750427,
				0.023471154272556305,
				0.24204707145690918,
				0.15325024724006653,
				0.37675660848617554,
				0.06289558112621307,
				0.3969947099685669,
				0.10949195921421051,
				0.31100335717201233,
				0.15587329864501953,
				0.3165658712387085,
				0.23049595952033997,
				0.20532669126987457,
				0.21212632954120636
			],
			"bbox": [
				[
					238.5107421875,
					759.9899291992188,
					301.8974609375,
					984.03662109375
				]
			],
			"bbox_score": 1.0
		},
		{
			"keypoints": [
				[
					1397.861185527362,
					691.5504792210679
				],
				[
					1401.0512537382187,
					686.9117234789536
				],
				[
					1396.3487467191806,
					686.58082352935
				],
				[
					1410.1336270064176,
					687.1717765492998
				],
				[
					1423.3743293075722,
					680.5040773033172
				],
				[
					1423.603952434994,
					710.0496602412092
				],
				[
					1434.1191756934165,
					707.7887009315369
				],
				[
					1441.865443740813,
					678.5572764670891
				],
				[
					1442.3572081314855,
					679.8738042480228
				],
				[
					1419.7635040584496,
					712.818065660771
				],
				[
					1405.6252411835073,
					702.7666781176162
				],
				[
					1424.2684838177656,
					715.0855337606146
				],
				[
					1429.3604232574257,
					715.7293659275941
				],
				[
					1424.8122465153563,
					794.6435903303144
				],
				[
					1426.6824266954939,
					793.8992485576697
				],
				[
					1429.947285222831,
					853.4040176744909
				],
				[
					1430.1606248536027,
					850.1372784512794
				]
			],
			"keypoint_scores": [
				0.15636613965034485,
				0.2528965473175049,
				0.13304200768470764,
				0.2581040859222412,
				0.08258046209812164,
				0.12481657415628433,
				0.08590473234653473,
				0.47061020135879517,
				0.22877904772758484,
				0.48392927646636963,
				0.21958988904953003,
				0.2648172080516815,
				0.1917443573474884,
				0.5764944553375244,
				0.4819844961166382,
				0.6438659429550171,
				0.5161333680152893
			],
			"bbox": [
				[
					1401.48681640625,
					691.079833984375,
					1452.988525390625,
					874.5347900390625
				]
			],
			"bbox_score": 1.0
		}
	]
}