{
	"meta_info": {
		"dataset_name": "coco",
		"num_keypoints": 17,
		"keypoint_id2name": {
			"0": "nose",
			"1": "left_eye",
			"2": "right_eye",
			"3": "left_ear",
			"4": "right_ear",
			"5": "left_shoulder",
			"6": "right_shoulder",
			"7": "left_elbow",
			"8": "right_elbow",
			"9": "left_wrist",
			"10": "right_wrist",
			"11": "left_hip",
			"12": "right_hip",
			"13": "left_knee",
			"14": "right_knee",
			"15": "left_ankle",
			"16": "right_ankle"
		},
		"keypoint_name2id": {
			"nose": 0,
			"left_eye": 1,
			"right_eye": 2,
			"left_ear": 3,
			"right_ear": 4,
			"left_shoulder": 5,
			"right_shoulder": 6,
			"left_elbow": 7,
			"right_elbow": 8,
			"left_wrist": 9,
			"right_wrist": 10,
			"left_hip": 11,
			"right_hip": 12,
			"left_knee": 13,
			"right_knee": 14,
			"left_ankle": 15,
			"right_ankle": 16
		},
		"upper_body_ids": [
			0,
			1,
			2,
			3,
			4,
			5,
			6,
			7,
			8,
			9,
			10
		],
		"lower_body_ids": [
			11,
			12,
			13,
			14,
			15,
			16
		],
		"flip_indices": [
			0,
			2,
			1,
			4,
			3,
			6,
			5,
			8,
			7,
			10,
			9,
			12,
			11,
			14,
			13,
			16,
			15
		],
		"flip_pairs": [
			[
				2,
				1
			],
			[
				1,
				2
			],
			[
				4,
				3
			],
			[
				3,
				4
			],
			[
				6,
				5
			],
			[
				5,
				6
			],
			[
				8,
				7
			],
			[
				7,
				8
			],
			[
				10,
				9
			],
			[
				9,
				10
			],
			[
				12,
				11
			],
			[
				11,
				12
			],
			[
				14,
				13
			],
			[
				13,
				14
			],
			[
				16,
				15
			],
			[
				15,
				16
			]
		],
		"keypoint_colors": {
			"__ndarray__": [
				[
					51,
					153,
					255
				],
				[
					51,
					153,
					255
				],
				[
					51,
					153,
					255
				],
				[
					51,
					153,
					255
				],
				[
					51,
					153,
					255
				],
				[
					0,
					255,
					0
				],
				[
					255,
					128,
					0
				],
				[
					0,
					255,
					0
				],
				[
					255,
					128,
					0
				],
				[
					0,
					255,
					0
				],
				[
					255,
					128,
					0
				],
				[
					0,
					255,
					0
				],
				[
					255,
					128,
					0
				],
				[
					0,
					255,
					0
				],
				[
					255,
					128,
					0
				],
				[
					0,
					255,
					0
				],
				[
					255,
					128,
					0
				]
			],
			"dtype": "uint8",
			"shape": [
				17,
				3
			],
			"Corder": true
		},
		"num_skeleton_links": 19,
		"skeleton_links": [
			[
				15,
				13
			],
			[
				13,
				11
			],
			[
				16,
				14
			],
			[
				14,
				12
			],
			[
				11,
				12
			],
			[
				5,
				11
			],
			[
				6,
				12
			],
			[
				5,
				6
			],
			[
				5,
				7
			],
			[
				6,
				8
			],
			[
				7,
				9
			],
			[
				8,
				10
			],
			[
				1,
				2
			],
			[
				0,
				1
			],
			[
				0,
				2
			],
			[
				1,
				3
			],
			[
				2,
				4
			],
			[
				3,
				5
			],
			[
				4,
				6
			]
		],
		"skeleton_link_colors": {
			"__ndarray__": [
				[
					0,
					255,
					0
				],
				[
					0,
					255,
					0
				],
				[
					255,
					128,
					0
				],
				[
					255,
					128,
					0
				],
				[
					51,
					153,
					255
				],
				[
					51,
					153,
					255
				],
				[
					51,
					153,
					255
				],
				[
					51,
					153,
					255
				],
				[
					0,
					255,
					0
				],
				[
					255,
					128,
					0
				],
				[
					0,
					255,
					0
				],
				[
					255,
					128,
					0
				],
				[
					51,
					153,
					255
				],
				[
					51,
					153,
					255
				],
				[
					51,
					153,
					255
				],
				[
					51,
					153,
					255
				],
				[
					51,
					153,
					255
				],
				[
					51,
					153,
					255
				],
				[
					51,
					153,
					255
				]
			],
			"dtype": "uint8",
			"shape": [
				19,
				3
			],
			"Corder": true
		},
		"dataset_keypoint_weights": {
			"__ndarray__": [
				1.0,
				1.0,
				1.0,
				1.0,
				1.0,
				1.0,
				1.0,
				1.2000000476837158,
				1.2000000476837158,
				1.5,
				1.5,
				1.0,
				1.0,
				1.2000000476837158,
				1.2000000476837158,
				1.5,
				1.5
			],
			"dtype": "float32",
			"shape": [
				17
			]
		},
		"sigmas": {
			"__ndarray__": [
				0.026000000536441803,
				0.02500000037252903,
				0.02500000037252903,
				0.03500000014901161,
				0.03500000014901161,
				0.07900000363588333,
				0.07900000363588333,
				0.07199999690055847,
				0.07199999690055847,
				0.06199999898672104,
				0.06199999898672104,
				0.10700000077486038,
				0.10700000077486038,
				0.08699999749660492,
				0.08699999749660492,
				0.08900000154972076,
				0.08900000154972076
			],
			"dtype": "float32",
			"shape": [
				17
			]
		},
		"CLASSES": [
			{
				"supercategory": "person",
				"id": 1,
				"name": "person",
				"keypoints": [
					"nose",
					"left_eye",
					"right_eye",
					"left_ear",
					"right_ear",
					"left_shoulder",
					"right_shoulder",
					"left_elbow",
					"right_elbow",
					"left_wrist",
					"right_wrist",
					"left_hip",
					"right_hip",
					"left_knee",
					"right_knee",
					"left_ankle",
					"right_ankle"
				],
				"skeleton": [
					[
						16,
						14
					],
					[
						14,
						12
					],
					[
						17,
						15
					],
					[
						15,
						13
					],
					[
						12,
						13
					],
					[
						6,
						12
					],
					[
						7,
						13
					],
					[
						6,
						7
					],
					[
						6,
						8
					],
					[
						7,
						9
					],
					[
						8,
						10
					],
					[
						9,
						11
					],
					[
						2,
						3
					],
					[
						1,
						2
					],
					[
						1,
						3
					],
					[
						2,
						4
					],
					[
						3,
						5
					],
					[
						4,
						6
					],
					[
						5,
						7
					]
				]
			}
		]
	},
	"instance_info": [
		{
			"keypoints": [
				[
					587.8927245193305,
					478.7450517817763
				],
				[
					589.617453932507,
					475.3244704907646
				],
				[
					584.9439687056497,
					475.17563061900796
				],
				[
					591.4726950402936,
					477.03456932509505
				],
				[
					578.4429650570097,
					476.5932832147412
				],
				[
					590.143205326583,
					493.4948047366454
				],
				[
					574.7558140377811,
					493.46400854238755
				],
				[
					594.1267312267904,
					514.5971590088235
				],
				[
					570.3463249008364,
					517.1969312775949
				],
				[
					599.1408947091525,
					532.4949673767135
				],
				[
					575.936347800312,
					534.5221734864505
				],
				[
					593.631348672744,
					534.3710654825471
				],
				[
					582.421846112385,
					535.6010259429006
				],
				[
					592.3892890140612,
					564.3893296163444
				],
				[
					583.8011961240752,
					563.9408218852421
				],
				[
					587.1304970372076,
					591.3155976032639
				],
				[
					583.1257061928417,
					592.403920211467
				]
			],
			"keypoint_scores": [
				0.901358962059021,
				0.8594866394996643,
				0.8865180015563965,
				0.7368454933166504,
				0.9335286617279053,
				0.8126871585845947,
				0.8826978206634521,
				0.7940447330474854,
				0.8325889706611633,
				0.7916622161865234,
				0.7789528369903564,
				0.7851841449737549,
				0.8413660526275635,
				0.8270477056503296,
				0.8567556142807007,
				0.8209095001220703,
				0.8209154605865479
			],
			"bbox": [
				[
					561.791259765625,
					463.0016784667969,
					608.8231201171875,
					610.9853515625
				]
			],
			"bbox_score": 1.0
		},
		{
			"keypoints": [
				[
					750.0480859319787,
					496.8583035042333
				],
				[
					751.418910178881,
					494.7119930031356
				],
				[
					749.7623017600516,
					495.02143922691016
				],
				[
					754.4181871930375,
					494.97111104103726
				],
				[
					750.9276996156606,
					495.9389566485502
				],
				[
					758.2930818133188,
					503.7847028419649
				],
				[
					755.0483960901004,
					503.99942697089307
				],
				[
					759.579856485564,
					514.8721472319975
				],
				[
					761.8028738920483,
					513.9818690922028
				],
				[
					754.3392108057913,
					523.5955396311705
				],
				[
					752.2590800997212,
					523.337123367382
				],
				[
					758.53014022824,
					527.4248852561402
				],
				[
					756.9196455750213,
					527.1146475275931
				],
				[
					759.2568904814881,
					541.0075785753351
				],
				[
					759.7558293079086,
					540.8190156210746
				],
				[
					760.7215848521384,
					552.4574410813115
				],
				[
					762.1384501597362,
					551.8889665502948
				]
			],
			"keypoint_scores": [
				0.8843967914581299,
				0.9117030501365662,
				0.9246530532836914,
				0.8986014723777771,
				0.5365673899650574,
				0.8719027638435364,
				0.6791503429412842,
				0.6652054786682129,
				0.42889103293418884,
				0.5655556917190552,
				0.44355493783950806,
				0.7778736352920532,
				0.6283909678459167,
				0.7255799770355225,
				0.6971383094787598,
				0.7834444046020508,
				0.6630018949508667
			],
			"bbox": [
				[
					745.887939453125,
					489.62847900390625,
					772.4445190429688,
					560.4061889648438
				]
			],
			"bbox_score": 1.0
		},
		{
			"keypoints": [
				[
					1139.2651117416087,
					493.44241278120455
				],
				[
					1138.0246365607377,
					491.9787309918257
				],
				[
					1138.6729741739828,
					491.82190816359855
				],
				[
					1129.5344641811234,
					490.6222243387675
				],
				[
					1136.4834020131768,
					491.28648037071105
				],
				[
					1128.4932914164247,
					498.77340049686677
				],
				[
					1133.9430096537974,
					499.23636607333947
				],
				[
					1128.1606435389344,
					509.0048405836184
				],
				[
					1132.4106532104704,
					509.1515905490752
				],
				[
					1130.9960038468869,
					516.9923304050342
				],
				[
					1134.2624319818185,
					519.010133935625
				],
				[
					1127.711018331437,
					518.863022570308
				],
				[
					1133.85244926423,
					519.0713248008443
				],
				[
					1122.0586936195132,
					533.1297546516963
				],
				[
					1139.8697233717417,
					531.1793074061621
				],
				[
					1116.5321591301522,
					547.3483371517098
				],
				[
					1144.393140768802,
					546.8462322792657
				]
			],
			"keypoint_scores": [
				0.48752903938293457,
				0.37621888518333435,
				0.4935072064399719,
				0.555908203125,
				0.6071592569351196,
				0.6451781392097473,
				0.6993675827980042,
				0.5002864599227905,
				0.6788821816444397,
				0.3752003312110901,
				0.759606122970581,
				0.4732564687728882,
				0.5381852388381958,
				0.44291675090789795,
				0.47278353571891785,
				0.6394804120063782,
				0.6544731855392456
			],
			"bbox": [
				[
					1113.343994140625,
					475.1045837402344,
					1151.636962890625,
					556.7257080078125
				]
			],
			"bbox_score": 1.0
		},
		{
			"keypoints": [
				[
					1224.2209871772368,
					475.63168457399945
				],
				[
					1225.2880236532715,
					473.6965557461208
				],
				[
					1222.6953834038716,
					473.8561569240232
				],
				[
					1226.7326571544165,
					474.34123459183365
				],
				[
					1220.6254108219052,
					474.4982327785436
				],
				[
					1226.9938332498973,
					483.0586993678354
				],
				[
					1216.1084409395394,
					482.5895977093379
				],
				[
					1228.333445442395,
					493.19575085250256
				],
				[
					1211.9933031466533,
					495.08375829809006
				],
				[
					1228.0576704709395,
					501.6854850787287
				],
				[
					1208.803484136137,
					505.6870388976513
				],
				[
					1224.6166634309404,
					503.36018604590527
				],
				[
					1217.0745330336429,
					503.9668077120423
				],
				[
					1223.50801641715,
					517.9346958181548
				],
				[
					1216.8884079819602,
					518.8181357408489
				],
				[
					1223.2726406346887,
					524.4445877016433
				],
				[
					1216.0472385039523,
					524.782373081124
				]
			],
			"keypoint_scores": [
				0.7245906591415405,
				0.7008482217788696,
				0.6744837760925293,
				0.6496732831001282,
				0.707923412322998,
				0.7334240674972534,
				0.782078742980957,
				0.49635544419288635,
				0.8206552267074585,
				0.2354818880558014,
				0.7786798477172852,
				0.6485403776168823,
				0.6961160898208618,
				0.4773227870464325,
				0.3795953392982483,
				0.25919678807258606,
				0.1954655945301056
			],
			"bbox": [
				[
					1208.077392578125,
					468.0281982421875,
					1234.401611328125,
					521.1825561523438
				]
			],
			"bbox_score": 1.0
		},
		{
			"keypoints": [
				[
					1302.7738328754513,
					488.59513668546833
				],
				[
					1304.9795110836342,
					485.7411842559526
				],
				[
					1301.4305042050667,
					485.78501072461654
				],
				[
					1309.2653177887003,
					486.923415384558
				],
				[
					1300.7886499708281,
					487.7948512757491
				],
				[
					1313.7888556504101,
					499.8109172811962
				],
				[
					1305.5579173062354,
					498.9727769665145
				],
				[
					1315.958507774053,
					518.9649300370576
				],
				[
					1302.755832072381,
					518.4652118118379
				],
				[
					1314.9346375168147,
					536.6467027644625
				],
				[
					1299.7920639496897,
					531.6708744831775
				],
				[
					1310.1400319780719,
					531.5482900287237
				],
				[
					1303.0454421370744,
					530.8063856328367
				],
				[
					1310.3861714649615,
					555.5877601844111
				],
				[
					1305.1438743572223,
					555.588782837522
				],
				[
					1310.2835274160425,
					571.2637844949325
				],
				[
					1306.792864802806,
					567.8633289821764
				]
			],
			"keypoint_scores": [
				0.7770154476165771,
				0.7524093389511108,
				0.8246310353279114,
				0.7980979681015015,
				0.6700968742370605,
				0.8234468698501587,
				0.8421928882598877,
				0.7789080739021301,
				0.5554878115653992,
				0.7497798204421997,
				0.691225528717041,
				0.6796779632568359,
				0.7627594470977783,
				0.5120267868041992,
				0.581550121307373,
				0.2823624014854431,
				0.409973680973053
			],
			"bbox": [
				[
					1296.098388671875,
					479.9852600097656,
					1327.4937744140625,
					560.4099731445312
				]
			],
			"bbox_score": 1.0
		},
		{
			"keypoints": [
				[
					1467.9192387144863,
					484.8901982739889
				],
				[
					1476.743530229369,
					485.28418881451387
				],
				[
					1466.753404766266,
					481.99156974725025
				],
				[
					1484.7469177681326,
					485.2659046093634
				],
				[
					1466.8451206714653,
					483.90906156510545
				],
				[
					1488.6908522254275,
					504.63814802215586
				],
				[
					1465.5317330246373,
					500.72117612968816
				],
				[
					1484.947311527534,
					498.390587027617
				],
				[
					1469.2802277123747,
					483.7118786151266
				],
				[
					1474.0375551261257,
					494.846454103882
				],
				[
					1472.1134780553164,
					494.46876933972817
				],
				[
					1484.8614732489489,
					511.9212592924513
				],
				[
					1469.7195341539996,
					511.9173159857746
				],
				[
					1475.2063343585596,
					497.38419282968005
				],
				[
					1475.4312930416154,
					497.2431688001823
				],
				[
					1474.1381034782255,
					495.97301752384135
				],
				[
					1473.0694121418028,
					495.21662625902707
				]
			],
			"keypoint_scores": [
				0.3013765215873718,
				0.26669806241989136,
				0.42219021916389465,
				0.2756006717681885,
				0.16887114942073822,
				0.07025228440761566,
				0.16544148325920105,
				0.03409488871693611,
				0.03128398582339287,
				0.05997712165117264,
				0.07774455845355988,
				0.025927476584911346,
				0.024759404361248016,
				0.06456494331359863,
				0.03863544389605522,
				0.1582828164100647,
				0.12907736003398895
			],
			"bbox": [
				[
					1460.865966796875,
					471.2825927734375,
					1486.95263671875,
					507.089599609375
				]
			],
			"bbox_score": 1.0
		}
	]
}