{
	"meta_info": {
		"dataset_name": "coco",
		"num_keypoints": 17,
		"keypoint_id2name": {
			"0": "nose",
			"1": "left_eye",
			"2": "right_eye",
			"3": "left_ear",
			"4": "right_ear",
			"5": "left_shoulder",
			"6": "right_shoulder",
			"7": "left_elbow",
			"8": "right_elbow",
			"9": "left_wrist",
			"10": "right_wrist",
			"11": "left_hip",
			"12": "right_hip",
			"13": "left_knee",
			"14": "right_knee",
			"15": "left_ankle",
			"16": "right_ankle"
		},
		"keypoint_name2id": {
			"nose": 0,
			"left_eye": 1,
			"right_eye": 2,
			"left_ear": 3,
			"right_ear": 4,
			"left_shoulder": 5,
			"right_shoulder": 6,
			"left_elbow": 7,
			"right_elbow": 8,
			"left_wrist": 9,
			"right_wrist": 10,
			"left_hip": 11,
			"right_hip": 12,
			"left_knee": 13,
			"right_knee": 14,
			"left_ankle": 15,
			"right_ankle": 16
		},
		"upper_body_ids": [
			0,
			1,
			2,
			3,
			4,
			5,
			6,
			7,
			8,
			9,
			10
		],
		"lower_body_ids": [
			11,
			12,
			13,
			14,
			15,
			16
		],
		"flip_indices": [
			0,
			2,
			1,
			4,
			3,
			6,
			5,
			8,
			7,
			10,
			9,
			12,
			11,
			14,
			13,
			16,
			15
		],
		"flip_pairs": [
			[
				2,
				1
			],
			[
				1,
				2
			],
			[
				4,
				3
			],
			[
				3,
				4
			],
			[
				6,
				5
			],
			[
				5,
				6
			],
			[
				8,
				7
			],
			[
				7,
				8
			],
			[
				10,
				9
			],
			[
				9,
				10
			],
			[
				12,
				11
			],
			[
				11,
				12
			],
			[
				14,
				13
			],
			[
				13,
				14
			],
			[
				16,
				15
			],
			[
				15,
				16
			]
		],
		"keypoint_colors": {
			"__ndarray__": [
				[
					51,
					153,
					255
				],
				[
					51,
					153,
					255
				],
				[
					51,
					153,
					255
				],
				[
					51,
					153,
					255
				],
				[
					51,
					153,
					255
				],
				[
					0,
					255,
					0
				],
				[
					255,
					128,
					0
				],
				[
					0,
					255,
					0
				],
				[
					255,
					128,
					0
				],
				[
					0,
					255,
					0
				],
				[
					255,
					128,
					0
				],
				[
					0,
					255,
					0
				],
				[
					255,
					128,
					0
				],
				[
					0,
					255,
					0
				],
				[
					255,
					128,
					0
				],
				[
					0,
					255,
					0
				],
				[
					255,
					128,
					0
				]
			],
			"dtype": "uint8",
			"shape": [
				17,
				3
			],
			"Corder": true
		},
		"num_skeleton_links": 19,
		"skeleton_links": [
			[
				15,
				13
			],
			[
				13,
				11
			],
			[
				16,
				14
			],
			[
				14,
				12
			],
			[
				11,
				12
			],
			[
				5,
				11
			],
			[
				6,
				12
			],
			[
				5,
				6
			],
			[
				5,
				7
			],
			[
				6,
				8
			],
			[
				7,
				9
			],
			[
				8,
				10
			],
			[
				1,
				2
			],
			[
				0,
				1
			],
			[
				0,
				2
			],
			[
				1,
				3
			],
			[
				2,
				4
			],
			[
				3,
				5
			],
			[
				4,
				6
			]
		],
		"skeleton_link_colors": {
			"__ndarray__": [
				[
					0,
					255,
					0
				],
				[
					0,
					255,
					0
				],
				[
					255,
					128,
					0
				],
				[
					255,
					128,
					0
				],
				[
					51,
					153,
					255
				],
				[
					51,
					153,
					255
				],
				[
					51,
					153,
					255
				],
				[
					51,
					153,
					255
				],
				[
					0,
					255,
					0
				],
				[
					255,
					128,
					0
				],
				[
					0,
					255,
					0
				],
				[
					255,
					128,
					0
				],
				[
					51,
					153,
					255
				],
				[
					51,
					153,
					255
				],
				[
					51,
					153,
					255
				],
				[
					51,
					153,
					255
				],
				[
					51,
					153,
					255
				],
				[
					51,
					153,
					255
				],
				[
					51,
					153,
					255
				]
			],
			"dtype": "uint8",
			"shape": [
				19,
				3
			],
			"Corder": true
		},
		"dataset_keypoint_weights": {
			"__ndarray__": [
				1.0,
				1.0,
				1.0,
				1.0,
				1.0,
				1.0,
				1.0,
				1.2000000476837158,
				1.2000000476837158,
				1.5,
				1.5,
				1.0,
				1.0,
				1.2000000476837158,
				1.2000000476837158,
				1.5,
				1.5
			],
			"dtype": "float32",
			"shape": [
				17
			]
		},
		"sigmas": {
			"__ndarray__": [
				0.026000000536441803,
				0.02500000037252903,
				0.02500000037252903,
				0.03500000014901161,
				0.03500000014901161,
				0.07900000363588333,
				0.07900000363588333,
				0.07199999690055847,
				0.07199999690055847,
				0.06199999898672104,
				0.06199999898672104,
				0.10700000077486038,
				0.10700000077486038,
				0.08699999749660492,
				0.08699999749660492,
				0.08900000154972076,
				0.08900000154972076
			],
			"dtype": "float32",
			"shape": [
				17
			]
		},
		"CLASSES": [
			{
				"supercategory": "person",
				"id": 1,
				"name": "person",
				"keypoints": [
					"nose",
					"left_eye",
					"right_eye",
					"left_ear",
					"right_ear",
					"left_shoulder",
					"right_shoulder",
					"left_elbow",
					"right_elbow",
					"left_wrist",
					"right_wrist",
					"left_hip",
					"right_hip",
					"left_knee",
					"right_knee",
					"left_ankle",
					"right_ankle"
				],
				"skeleton": [
					[
						16,
						14
					],
					[
						14,
						12
					],
					[
						17,
						15
					],
					[
						15,
						13
					],
					[
						12,
						13
					],
					[
						6,
						12
					],
					[
						7,
						13
					],
					[
						6,
						7
					],
					[
						6,
						8
					],
					[
						7,
						9
					],
					[
						8,
						10
					],
					[
						9,
						11
					],
					[
						2,
						3
					],
					[
						1,
						2
					],
					[
						1,
						3
					],
					[
						2,
						4
					],
					[
						3,
						5
					],
					[
						4,
						6
					],
					[
						5,
						7
					]
				]
			}
		]
	},
	"instance_info": [
		{
			"keypoints": [
				[
					564.9137196642287,
					548.7395562065972
				],
				[
					560.8327078312,
					541.7071436321921
				],
				[
					553.5477885794132,
					543.1344943576387
				],
				[
					574.1229994753576,
					556.0003177703375
				],
				[
					562.9133898146611,
					556.4393833705358
				],
				[
					640.8934313185673,
					595.2230592757937
				],
				[
					594.0295345225234,
					589.2140997023807
				],
				[
					654.8183100274268,
					613.6316499255954
				],
				[
					596.1540449426527,
					611.9170464409722
				],
				[
					601.7658379737368,
					634.9639214409722
				],
				[
					539.7329192465925,
					620.9928772941466
				],
				[
					708.9219827854886,
					651.3151429191466
				],
				[
					618.574433022357,
					644.9616737971228
				],
				[
					623.3715041140294,
					672.7456519717261
				],
				[
					580.3443486639794,
					666.920572916667
				],
				[
					589.5801690284243,
					709.3341936383927
				],
				[
					518.5154756586603,
					692.506510416667
				]
			],
			"keypoint_scores": [
				0.5298988819122314,
				0.5258216261863708,
				0.5368722081184387,
				0.4040274918079376,
				0.4100967347621918,
				0.4784216284751892,
				0.5342394113540649,
				0.5571784973144531,
				0.5785559415817261,
				0.5938304662704468,
				0.590661883354187,
				0.4497198462486267,
				0.4863819479942322,
				0.48713934421539307,
				0.491638720035553,
				0.526328444480896,
				0.5088194012641907
			],
			"bbox": [
				[
					0.0,
					0.0,
					1920.0,
					1080.0
				]
			],
			"bbox_score": 1.0
		}
	]
}