{
	"meta_info": {
		"dataset_name": "coco",
		"num_keypoints": 17,
		"keypoint_id2name": {
			"0": "nose",
			"1": "left_eye",
			"2": "right_eye",
			"3": "left_ear",
			"4": "right_ear",
			"5": "left_shoulder",
			"6": "right_shoulder",
			"7": "left_elbow",
			"8": "right_elbow",
			"9": "left_wrist",
			"10": "right_wrist",
			"11": "left_hip",
			"12": "right_hip",
			"13": "left_knee",
			"14": "right_knee",
			"15": "left_ankle",
			"16": "right_ankle"
		},
		"keypoint_name2id": {
			"nose": 0,
			"left_eye": 1,
			"right_eye": 2,
			"left_ear": 3,
			"right_ear": 4,
			"left_shoulder": 5,
			"right_shoulder": 6,
			"left_elbow": 7,
			"right_elbow": 8,
			"left_wrist": 9,
			"right_wrist": 10,
			"left_hip": 11,
			"right_hip": 12,
			"left_knee": 13,
			"right_knee": 14,
			"left_ankle": 15,
			"right_ankle": 16
		},
		"upper_body_ids": [
			0,
			1,
			2,
			3,
			4,
			5,
			6,
			7,
			8,
			9,
			10
		],
		"lower_body_ids": [
			11,
			12,
			13,
			14,
			15,
			16
		],
		"flip_indices": [
			0,
			2,
			1,
			4,
			3,
			6,
			5,
			8,
			7,
			10,
			9,
			12,
			11,
			14,
			13,
			16,
			15
		],
		"flip_pairs": [
			[
				2,
				1
			],
			[
				1,
				2
			],
			[
				4,
				3
			],
			[
				3,
				4
			],
			[
				6,
				5
			],
			[
				5,
				6
			],
			[
				8,
				7
			],
			[
				7,
				8
			],
			[
				10,
				9
			],
			[
				9,
				10
			],
			[
				12,
				11
			],
			[
				11,
				12
			],
			[
				14,
				13
			],
			[
				13,
				14
			],
			[
				16,
				15
			],
			[
				15,
				16
			]
		],
		"keypoint_colors": {
			"__ndarray__": [
				[
					51,
					153,
					255
				],
				[
					51,
					153,
					255
				],
				[
					51,
					153,
					255
				],
				[
					51,
					153,
					255
				],
				[
					51,
					153,
					255
				],
				[
					0,
					255,
					0
				],
				[
					255,
					128,
					0
				],
				[
					0,
					255,
					0
				],
				[
					255,
					128,
					0
				],
				[
					0,
					255,
					0
				],
				[
					255,
					128,
					0
				],
				[
					0,
					255,
					0
				],
				[
					255,
					128,
					0
				],
				[
					0,
					255,
					0
				],
				[
					255,
					128,
					0
				],
				[
					0,
					255,
					0
				],
				[
					255,
					128,
					0
				]
			],
			"dtype": "uint8",
			"shape": [
				17,
				3
			],
			"Corder": true
		},
		"num_skeleton_links": 19,
		"skeleton_links": [
			[
				15,
				13
			],
			[
				13,
				11
			],
			[
				16,
				14
			],
			[
				14,
				12
			],
			[
				11,
				12
			],
			[
				5,
				11
			],
			[
				6,
				12
			],
			[
				5,
				6
			],
			[
				5,
				7
			],
			[
				6,
				8
			],
			[
				7,
				9
			],
			[
				8,
				10
			],
			[
				1,
				2
			],
			[
				0,
				1
			],
			[
				0,
				2
			],
			[
				1,
				3
			],
			[
				2,
				4
			],
			[
				3,
				5
			],
			[
				4,
				6
			]
		],
		"skeleton_link_colors": {
			"__ndarray__": [
				[
					0,
					255,
					0
				],
				[
					0,
					255,
					0
				],
				[
					255,
					128,
					0
				],
				[
					255,
					128,
					0
				],
				[
					51,
					153,
					255
				],
				[
					51,
					153,
					255
				],
				[
					51,
					153,
					255
				],
				[
					51,
					153,
					255
				],
				[
					0,
					255,
					0
				],
				[
					255,
					128,
					0
				],
				[
					0,
					255,
					0
				],
				[
					255,
					128,
					0
				],
				[
					51,
					153,
					255
				],
				[
					51,
					153,
					255
				],
				[
					51,
					153,
					255
				],
				[
					51,
					153,
					255
				],
				[
					51,
					153,
					255
				],
				[
					51,
					153,
					255
				],
				[
					51,
					153,
					255
				]
			],
			"dtype": "uint8",
			"shape": [
				19,
				3
			],
			"Corder": true
		},
		"dataset_keypoint_weights": {
			"__ndarray__": [
				1.0,
				1.0,
				1.0,
				1.0,
				1.0,
				1.0,
				1.0,
				1.2000000476837158,
				1.2000000476837158,
				1.5,
				1.5,
				1.0,
				1.0,
				1.2000000476837158,
				1.2000000476837158,
				1.5,
				1.5
			],
			"dtype": "float32",
			"shape": [
				17
			]
		},
		"sigmas": {
			"__ndarray__": [
				0.026000000536441803,
				0.02500000037252903,
				0.02500000037252903,
				0.03500000014901161,
				0.03500000014901161,
				0.07900000363588333,
				0.07900000363588333,
				0.07199999690055847,
				0.07199999690055847,
				0.06199999898672104,
				0.06199999898672104,
				0.10700000077486038,
				0.10700000077486038,
				0.08699999749660492,
				0.08699999749660492,
				0.08900000154972076,
				0.08900000154972076
			],
			"dtype": "float32",
			"shape": [
				17
			]
		}
	},
	"instance_info": [
		{
			"keypoints": [
				[
					196.36184483024283,
					703.4510877602144
				],
				[
					196.07418474333517,
					701.5285232265928
				],
				[
					194.90460949024543,
					701.7613576724559
				],
				[
					188.08745074047005,
					702.825010970369
				],
				[
					191.7430388639951,
					703.0937128388339
				],
				[
					187.08015024909588,
					713.5021370611826
				],
				[
					189.8271441032424,
					714.2921747567339
				],
				[
					196.75056327771313,
					727.9939516377474
				],
				[
					190.93128886524255,
					729.987702946253
				],
				[
					199.98713254515252,
					729.284506047843
				],
				[
					200.18362921306198,
					732.362211934847
				],
				[
					187.74198276338606,
					745.3501631330518
				],
				[
					192.8717575841738,
					746.2466738825606
				],
				[
					183.12150864070713,
					766.6472761490472
				],
				[
					203.1324927947847,
					767.8314708990446
				],
				[
					168.5115628225699,
					786.1928244609347
				],
				[
					208.99561426205997,
					792.3595378229058
				]
			],
			"keypoint_scores": [
				0.7126078605651855,
				0.5933128595352173,
				0.7226532697677612,
				0.38802459836006165,
				0.7443826794624329,
				0.4876304864883423,
				0.8029842376708984,
				0.2852652370929718,
				0.8266334533691406,
				0.5458915829658508,
				0.8100345134735107,
				0.6028367280960083,
				0.726873517036438,
				0.7109084129333496,
				0.7125725150108337,
				0.738052248954773,
				0.7658054232597351
			],
			"bbox": [
				[
					161.21571350097656,
					701.32275390625,
					221.7162322998047,
					801.2005004882812
				]
			],
			"bbox_score": 1.0
		},
		{
			"keypoints": [
				[
					797.1942462212297,
					720.0633193993896
				],
				[
					797.1862407808931,
					718.1958066388479
				],
				[
					796.2802901576506,
					718.0631354642727
				],
				[
					780.9037553110925,
					716.0370230123277
				],
				[
					790.9237973738295,
					717.1509647621842
				],
				[
					778.22617441407,
					725.5173403587282
				],
				[
					787.8438382783492,
					727.0908300914471
				],
				[
					765.1003335276037,
					742.8481860292086
				],
				[
					797.9984663218988,
					737.5952717190958
				],
				[
					804.8469693919054,
					725.6731636401655
				],
				[
					807.8326086038575,
					729.320454606318
				],
				[
					777.564301963529,
					754.9048566362281
				],
				[
					787.2555651745333,
					755.790000381563
				],
				[
					776.196995180956,
					784.856704306082
				],
				[
					800.3769694284134,
					782.0706823843675
				],
				[
					753.2621253031366,
					805.8677892908546
				],
				[
					805.5773463748282,
					814.8223685558371
				]
			],
			"keypoint_scores": [
				0.39978915452957153,
				0.3344844579696655,
				0.4599846601486206,
				0.5391832590103149,
				0.5785380005836487,
				0.741241455078125,
				0.7024821043014526,
				0.34924113750457764,
				0.7519168853759766,
				0.4019436836242676,
				0.7332508563995361,
				0.621110200881958,
				0.6777374744415283,
				0.7615185976028442,
				0.7052289843559265,
				0.7699368000030518,
				0.7944753170013428
			],
			"bbox": [
				[
					745.3884887695312,
					698.7930297851562,
					817.939697265625,
					826.9400634765625
				]
			],
			"bbox_score": 1.0
		},
		{
			"keypoints": [
				[
					1362.4124395346728,
					664.3152627788701
				],
				[
					1361.8915973817384,
					661.7549272189004
				],
				[
					1372.71540910049,
					661.4487601170858
				],
				[
					1362.9494339290754,
					663.7119114174913
				],
				[
					1375.6423255698526,
					662.1673003218533
				],
				[
					1361.4695891139663,
					676.784474974391
				],
				[
					1383.6811540210463,
					674.2798879946913
				],
				[
					1359.8058777596245,
					693.5642726889346
				],
				[
					1391.3414583704582,
					690.1077697467113
				],
				[
					1360.8814631016676,
					709.1585323183265
				],
				[
					1389.044041123553,
					694.7399485987548
				],
				[
					1368.5983593572569,
					703.9546770469659
				],
				[
					1381.4468444465156,
					703.1073221262824
				],
				[
					1374.116592232922,
					725.6789874176213
				],
				[
					1378.9454189410096,
					724.4137029185677
				],
				[
					1378.930569852781,
					745.6393328863196
				],
				[
					1379.2572917080986,
					745.8468175911593
				]
			],
			"keypoint_scores": [
				0.18696212768554688,
				0.2897387444972992,
				0.19609639048576355,
				0.6610062122344971,
				0.7328164577484131,
				0.7831422090530396,
				0.821587085723877,
				0.6171829700469971,
				0.7514083981513977,
				0.62152099609375,
				0.3638385534286499,
				0.6218194961547852,
				0.636418879032135,
				0.5440945625305176,
				0.7169468998908997,
				0.480917751789093,
				0.6145362854003906
			],
			"bbox": [
				[
					1354.000244140625,
					656.1593627929688,
					1394.28662109375,
					756.3128051757812
				]
			],
			"bbox_score": 1.0
		},
		{
			"keypoints": [
				[
					1438.3029740337504,
					674.5707328309308
				],
				[
					1438.7573948785791,
					673.085247930253
				],
				[
					1436.2318636973494,
					673.0638232224488
				],
				[
					1426.5471794112802,
					674.107096448039
				],
				[
					1433.267771343111,
					673.775995725885
				],
				[
					1423.8652886925565,
					682.8939628152488
				],
				[
					1435.508582353274,
					682.8074569912334
				],
				[
					1421.4306801958578,
					693.6045913286868
				],
				[
					1440.297394689413,
					692.9608230128181
				],
				[
					1423.879689689773,
					705.5732319494488
				],
				[
					1444.5503926841263,
					699.8655104586866
				],
				[
					1426.7232638351359,
					705.2548175888342
				],
				[
					1433.5700611678383,
					705.5729140431947
				],
				[
					1432.7293592497215,
					722.5552297420578
				],
				[
					1434.8589504187112,
					723.1510023650093
				],
				[
					1430.1324076448911,
					736.6708217194149
				],
				[
					1430.65960105551,
					738.74912434517
				]
			],
			"keypoint_scores": [
				0.4385913908481598,
				0.3759283125400543,
				0.5068375468254089,
				0.5747634172439575,
				0.6961400508880615,
				0.6691601276397705,
				0.5160988569259644,
				0.6155181527137756,
				0.4080524444580078,
				0.2645703852176666,
				0.49626556038856506,
				0.5331776142120361,
				0.5471135377883911,
				0.4597642421722412,
				0.584298312664032,
				0.46031469106674194,
				0.507317066192627
			],
			"bbox": [
				[
					1417.904052734375,
					669.498291015625,
					1448.1483154296875,
					741.2965087890625
				]
			],
			"bbox_score": 1.0
		},
		{
			"keypoints": [
				[
					1344.5594696251053,
					674.2265950872259
				],
				[
					1344.906668973649,
					672.0389510419332
				],
				[
					1345.4667397352962,
					671.8195514721987
				],
				[
					1343.0907262574215,
					673.2166178242012
				],
				[
					1351.0813016361276,
					672.038593046437
				],
				[
					1339.6856036254937,
					686.1943531553742
				],
				[
					1356.4685664523001,
					683.3869819993593
				],
				[
					1335.236909064893,
					700.0843274430889
				],
				[
					1359.96741142566,
					698.9529509547532
				],
				[
					1335.2738859791732,
					712.0824357788994
				],
				[
					1360.8759281988248,
					711.7621220766562
				],
				[
					1343.8519958080176,
					713.3966667709525
				],
				[
					1354.2647742698437,
					712.9284824753912
				],
				[
					1346.5061375691903,
					733.551296514034
				],
				[
					1350.8651428914916,
					732.7480874848072
				],
				[
					1349.7247171227255,
					754.069723494787
				],
				[
					1350.5800985969333,
					752.9497290488263
				]
			],
			"keypoint_scores": [
				0.6302047967910767,
				0.6957900524139404,
				0.5804703831672668,
				0.8151752948760986,
				0.8409751653671265,
				0.8078405857086182,
				0.7569475173950195,
				0.6269855499267578,
				0.6585575342178345,
				0.4435890316963196,
				0.6849000453948975,
				0.6871092915534973,
				0.7111978530883789,
				0.743933916091919,
				0.7636832594871521,
				0.7095291614532471,
				0.6550438404083252
			],
			"bbox": [
				[
					1329.18994140625,
					663.2916259765625,
					1363.216796875,
					760.814453125
				]
			],
			"bbox_score": 1.0
		},
		{
			"keypoints": [
				[
					683.4767764036391,
					681.5962784416793
				],
				[
					682.6711809606148,
					681.6377955858984
				],
				[
					681.8063850945232,
					681.7100598446834
				],
				[
					674.3823878416302,
					681.976402422513
				],
				[
					679.9875181458347,
					681.5847919410347
				],
				[
					667.0490601953727,
					686.8379934431161
				],
				[
					681.3882833297586,
					688.7502683577703
				],
				[
					666.9892384124928,
					706.0172563492475
				],
				[
					679.5713440642675,
					708.0398343378814
				],
				[
					683.1477590440986,
					681.7171491205853
				],
				[
					683.4665313056305,
					687.487193724145
				],
				[
					667.1210498668614,
					723.7728352770339
				],
				[
					674.5156670750832,
					725.6591137466926
				],
				[
					667.5442448250486,
					767.0408283714075
				],
				[
					678.1623739952623,
					765.618123514319
				],
				[
					650.1332683007953,
					813.8157144291714
				],
				[
					690.3412611621873,
					800.6627195972638
				]
			],
			"keypoint_scores": [
				0.10217516124248505,
				0.09980402141809464,
				0.10168161243200302,
				0.058638542890548706,
				0.10914081335067749,
				0.6311043500900269,
				0.5899807810783386,
				0.24675627052783966,
				0.6609550714492798,
				0.2369593381881714,
				0.4543774127960205,
				0.45430389046669006,
				0.5738643407821655,
				0.3398228883743286,
				0.42463481426239014,
				0.3607005178928375,
				0.27981269359588623
			],
			"bbox": [
				[
					639.4618530273438,
					699.067138671875,
					698.3473510742188,
					827.6656494140625
				]
			],
			"bbox_score": 1.0
		}
	]
}