{
	"meta_info": {
		"dataset_name": "coco",
		"num_keypoints": 17,
		"keypoint_id2name": {
			"0": "nose",
			"1": "left_eye",
			"2": "right_eye",
			"3": "left_ear",
			"4": "right_ear",
			"5": "left_shoulder",
			"6": "right_shoulder",
			"7": "left_elbow",
			"8": "right_elbow",
			"9": "left_wrist",
			"10": "right_wrist",
			"11": "left_hip",
			"12": "right_hip",
			"13": "left_knee",
			"14": "right_knee",
			"15": "left_ankle",
			"16": "right_ankle"
		},
		"keypoint_name2id": {
			"nose": 0,
			"left_eye": 1,
			"right_eye": 2,
			"left_ear": 3,
			"right_ear": 4,
			"left_shoulder": 5,
			"right_shoulder": 6,
			"left_elbow": 7,
			"right_elbow": 8,
			"left_wrist": 9,
			"right_wrist": 10,
			"left_hip": 11,
			"right_hip": 12,
			"left_knee": 13,
			"right_knee": 14,
			"left_ankle": 15,
			"right_ankle": 16
		},
		"upper_body_ids": [
			0,
			1,
			2,
			3,
			4,
			5,
			6,
			7,
			8,
			9,
			10
		],
		"lower_body_ids": [
			11,
			12,
			13,
			14,
			15,
			16
		],
		"flip_indices": [
			0,
			2,
			1,
			4,
			3,
			6,
			5,
			8,
			7,
			10,
			9,
			12,
			11,
			14,
			13,
			16,
			15
		],
		"flip_pairs": [
			[
				2,
				1
			],
			[
				1,
				2
			],
			[
				4,
				3
			],
			[
				3,
				4
			],
			[
				6,
				5
			],
			[
				5,
				6
			],
			[
				8,
				7
			],
			[
				7,
				8
			],
			[
				10,
				9
			],
			[
				9,
				10
			],
			[
				12,
				11
			],
			[
				11,
				12
			],
			[
				14,
				13
			],
			[
				13,
				14
			],
			[
				16,
				15
			],
			[
				15,
				16
			]
		],
		"keypoint_colors": {
			"__ndarray__": [
				[
					51,
					153,
					255
				],
				[
					51,
					153,
					255
				],
				[
					51,
					153,
					255
				],
				[
					51,
					153,
					255
				],
				[
					51,
					153,
					255
				],
				[
					0,
					255,
					0
				],
				[
					255,
					128,
					0
				],
				[
					0,
					255,
					0
				],
				[
					255,
					128,
					0
				],
				[
					0,
					255,
					0
				],
				[
					255,
					128,
					0
				],
				[
					0,
					255,
					0
				],
				[
					255,
					128,
					0
				],
				[
					0,
					255,
					0
				],
				[
					255,
					128,
					0
				],
				[
					0,
					255,
					0
				],
				[
					255,
					128,
					0
				]
			],
			"dtype": "uint8",
			"shape": [
				17,
				3
			],
			"Corder": true
		},
		"num_skeleton_links": 19,
		"skeleton_links": [
			[
				15,
				13
			],
			[
				13,
				11
			],
			[
				16,
				14
			],
			[
				14,
				12
			],
			[
				11,
				12
			],
			[
				5,
				11
			],
			[
				6,
				12
			],
			[
				5,
				6
			],
			[
				5,
				7
			],
			[
				6,
				8
			],
			[
				7,
				9
			],
			[
				8,
				10
			],
			[
				1,
				2
			],
			[
				0,
				1
			],
			[
				0,
				2
			],
			[
				1,
				3
			],
			[
				2,
				4
			],
			[
				3,
				5
			],
			[
				4,
				6
			]
		],
		"skeleton_link_colors": {
			"__ndarray__": [
				[
					0,
					255,
					0
				],
				[
					0,
					255,
					0
				],
				[
					255,
					128,
					0
				],
				[
					255,
					128,
					0
				],
				[
					51,
					153,
					255
				],
				[
					51,
					153,
					255
				],
				[
					51,
					153,
					255
				],
				[
					51,
					153,
					255
				],
				[
					0,
					255,
					0
				],
				[
					255,
					128,
					0
				],
				[
					0,
					255,
					0
				],
				[
					255,
					128,
					0
				],
				[
					51,
					153,
					255
				],
				[
					51,
					153,
					255
				],
				[
					51,
					153,
					255
				],
				[
					51,
					153,
					255
				],
				[
					51,
					153,
					255
				],
				[
					51,
					153,
					255
				],
				[
					51,
					153,
					255
				]
			],
			"dtype": "uint8",
			"shape": [
				19,
				3
			],
			"Corder": true
		},
		"dataset_keypoint_weights": {
			"__ndarray__": [
				1.0,
				1.0,
				1.0,
				1.0,
				1.0,
				1.0,
				1.0,
				1.2000000476837158,
				1.2000000476837158,
				1.5,
				1.5,
				1.0,
				1.0,
				1.2000000476837158,
				1.2000000476837158,
				1.5,
				1.5
			],
			"dtype": "float32",
			"shape": [
				17
			]
		},
		"sigmas": {
			"__ndarray__": [
				0.026000000536441803,
				0.02500000037252903,
				0.02500000037252903,
				0.03500000014901161,
				0.03500000014901161,
				0.07900000363588333,
				0.07900000363588333,
				0.07199999690055847,
				0.07199999690055847,
				0.06199999898672104,
				0.06199999898672104,
				0.10700000077486038,
				0.10700000077486038,
				0.08699999749660492,
				0.08699999749660492,
				0.08900000154972076,
				0.08900000154972076
			],
			"dtype": "float32",
			"shape": [
				17
			]
		}
	},
	"instance_info": [
		{
			"keypoints": [
				[
					142.57037956553123,
					639.651207675833
				],
				[
					140.25800553826272,
					636.0075477793123
				],
				[
					140.56861501592897,
					636.5017062298097
				],
				[
					124.44743569304751,
					639.0098887481893
				],
				[
					138.0907364077148,
					639.4237282070306
				],
				[
					114.6114537219459,
					657.2549192890458
				],
				[
					137.36834372087174,
					657.0924796077472
				],
				[
					108.72536566838446,
					679.2735458701666
				],
				[
					139.43718133936605,
					681.6101971781629
				],
				[
					108.90366052753481,
					697.8753377756968
				],
				[
					140.8098949120136,
					701.5988536576873
				],
				[
					114.31728744212981,
					700.8050496817533
				],
				[
					130.36283817379166,
					701.1081576882362
				],
				[
					114.74433499835698,
					729.0040589830273
				],
				[
					134.3390159106645,
					728.4000170860672
				],
				[
					107.904050703275,
					749.840545214696
				],
				[
					134.23134585114184,
					754.5063994702982
				]
			],
			"keypoint_scores": [
				0.5838660001754761,
				0.41963911056518555,
				0.6893550157546997,
				0.8778178691864014,
				0.7885494232177734,
				0.8538559675216675,
				0.8944838047027588,
				0.7793138027191162,
				0.7879934906959534,
				0.7039692401885986,
				0.8202582597732544,
				0.7199410200119019,
				0.7418451905250549,
				0.7768620252609253,
				0.8116344213485718,
				0.7430529594421387,
				0.7918837070465088
			],
			"bbox": [
				[
					99.41239929199219,
					626.7567138671875,
					146.07102966308594,
					759.74072265625
				]
			],
			"bbox_score": 1.0
		},
		{
			"keypoints": [
				[
					723.7628673589411,
					671.7775055987255
				],
				[
					725.7664506364108,
					668.6885290342739
				],
				[
					723.3090364872614,
					668.5499727231929
				],
				[
					731.8997598589891,
					668.7024146414474
				],
				[
					728.2912587521924,
					668.4328703564693
				],
				[
					741.18413799829,
					683.0064777791032
				],
				[
					729.6953594966159,
					682.8268443489242
				],
				[
					744.1381256375722,
					703.338801997874
				],
				[
					729.5155476118076,
					702.7158696296697
				],
				[
					740.0048581469888,
					719.3550633104991
				],
				[
					725.4695934132491,
					715.3843246782398
				],
				[
					738.3674089062744,
					720.2391739163265
				],
				[
					732.9953825285025,
					719.031564585087
				],
				[
					727.3468217201676,
					745.9011632950564
				],
				[
					743.7690826520724,
					747.9865461432473
				],
				[
					722.8437889879749,
					774.1377151816537
				],
				[
					752.0617134936372,
					775.7752704763127
				]
			],
			"keypoint_scores": [
				0.8066425323486328,
				0.7293772101402283,
				0.7377443909645081,
				0.7886072397232056,
				0.36255472898483276,
				0.6725249290466309,
				0.5802310705184937,
				0.6393229961395264,
				0.5109155178070068,
				0.6881651282310486,
				0.5913569927215576,
				0.6743615865707397,
				0.5742491483688354,
				0.6850478649139404,
				0.6302676200866699,
				0.6190038919448853,
				0.5742660760879517
			],
			"bbox": [
				[
					708.8314208984375,
					655.5452270507812,
					763.287353515625,
					786.4693603515625
				]
			],
			"bbox_score": 1.0
		},
		{
			"keypoints": [
				[
					1877.5898388935293,
					640.900709439956
				],
				[
					1831.6064651356414,
					581.7042535064475
				],
				[
					1819.3157450716863,
					575.8692552292396
				],
				[
					1808.072519541619,
					512.3549422201893
				],
				[
					1483.7253380138031,
					255.08412272642772
				],
				[
					1889.644372712979,
					615.5812646549136
				],
				[
					1485.2358115786449,
					42.46831093358969
				],
				[
					1605.0013825672659,
					338.54217860262315
				],
				[
					1604.5871338216548,
					323.2109910775981
				],
				[
					1892.800850087935,
					521.0658996478907
				],
				[
					1884.8987756654064,
					502.45110758772444
				],
				[
					1584.7838235095421,
					272.3437959791886
				],
				[
					1631.4405787401297,
					272.7480984360334
				],
				[
					1605.413785677423,
					354.90389212557955
				],
				[
					1611.397087897828,
					334.2495852929378
				],
				[
					1894.2620975250734,
					607.7028606564754
				],
				[
					1888.5481754405464,
					563.403313045109
				]
			],
			"keypoint_scores": [
				0.13934452831745148,
				0.22085964679718018,
				0.19837746024131775,
				0.10278201103210449,
				0.04931418597698212,
				0.06011543795466423,
				0.023689029738307,
				0.10073070228099823,
				0.13847926259040833,
				0.07711213827133179,
				0.04409371688961983,
				0.03659798949956894,
				0.03877417743206024,
				0.18115969002246857,
				0.20563535392284393,
				0.1850104182958603,
				0.1435316801071167
			],
			"bbox": [
				[
					1401.0758056640625,
					2.0023269653320312,
					1919.03857421875,
					726.05078125
				]
			],
			"bbox_score": 1.0
		},
		{
			"keypoints": [
				[
					1540.7151975815996,
					671.0398509886091
				],
				[
					1541.450012416959,
					668.6182366707882
				],
				[
					1542.4501806771868,
					668.7586703951242
				],
				[
					1542.6234070482997,
					669.7125078414083
				],
				[
					1553.8791685769374,
					669.3778648348431
				],
				[
					1542.1806809815362,
					682.5324553709605
				],
				[
					1560.1019660755076,
					682.9036885606391
				],
				[
					1538.7696736541575,
					700.0106420443303
				],
				[
					1566.8601186739954,
					701.250682229512
				],
				[
					1538.6687777712978,
					713.0271696593586
				],
				[
					1564.4941632845055,
					710.8465575173706
				],
				[
					1548.551910230994,
					716.6695412361184
				],
				[
					1562.0407290914409,
					716.083154703023
				],
				[
					1546.7152506152931,
					738.9833605387073
				],
				[
					1562.5218269377588,
					739.2026618048862
				],
				[
					1548.6361320973672,
					755.2269248824081
				],
				[
					1565.0313247197403,
					755.7194622057132
				]
			],
			"keypoint_scores": [
				0.6178326606750488,
				0.7250411510467529,
				0.44983145594596863,
				0.874974250793457,
				0.8579860925674438,
				0.8414479494094849,
				0.8499855995178223,
				0.6791684627532959,
				0.6617991924285889,
				0.40714341402053833,
				0.4371814727783203,
				0.6208344101905823,
				0.6153599619865417,
				0.4822077751159668,
				0.4814088046550751,
				0.39187848567962646,
				0.349364697933197
			],
			"bbox": [
				[
					1530.5570068359375,
					654.9996337890625,
					1578.40380859375,
					758.8908081054688
				]
			],
			"bbox_score": 1.0
		},
		{
			"keypoints": [
				[
					665.7795579589522,
					664.8744450935026
				],
				[
					666.5225053341132,
					680.1139372723306
				],
				[
					663.0238887240565,
					680.2328887707325
				],
				[
					658.0355232416572,
					664.8720227181478
				],
				[
					663.44333073214,
					679.5256166944497
				],
				[
					668.5830097172862,
					668.9546680672554
				],
				[
					659.1666725757742,
					664.8761899722684
				],
				[
					675.7656067865807,
					669.8614580131876
				],
				[
					656.1440885852093,
					669.6189746007897
				],
				[
					665.6387760687024,
					664.8574957796397
				],
				[
					665.3970531542035,
					678.898884521076
				],
				[
					668.4273360522732,
					669.041321691952
				],
				[
					658.3297791090615,
					667.2985758330004
				],
				[
					667.9519849999022,
					698.5527596583872
				],
				[
					660.7889405040933,
					697.9764482763795
				],
				[
					676.5734897689393,
					716.1093960441982
				],
				[
					658.3165268300024,
					712.367278230651
				]
			],
			"keypoint_scores": [
				0.05191344395279884,
				0.08268803358078003,
				0.05225890502333641,
				0.028765888884663582,
				0.05846136808395386,
				0.06574049592018127,
				0.06433666497468948,
				0.04074110835790634,
				0.06817358732223511,
				0.053305238485336304,
				0.06477329134941101,
				0.11607656627893448,
				0.07655340433120728,
				0.16834625601768494,
				0.15721426904201508,
				0.1355639100074768,
				0.14776167273521423
			],
			"bbox": [
				[
					652.3008422851562,
					671.4985961914062,
					674.0877075195312,
					720.5794677734375
				]
			],
			"bbox_score": 1.0
		}
	]
}